{
  "@context": {
    "ldp": "http://www.w3.org/ns/ldp#",
    "schema": "http://schema.org/",
    "fedora": "http://fedora.info/definitions/v4/repository#",
    "webac": "http://fedora.info/definitions/v4/webac#",
    "acl": "http://www.w3.org/ns/auth/acl#",
    "ucdlib": "http://digital.ucdavis.edu/schema#",
    "ebucore": "http://www.ebu.ch/metadata/ontologies/ebucore/ebucore#"
  },
  "@id": "",
  "@type": [
    "schema:CreativeWork",
    "schema:ImageObject",
    "schema:Book",
    "http://fedora.info/definitions/v4/repository#ArchivalGroup"
  ],
  "schema:about": [
    {
      "@id": "http://id.worldcat.org/fast/531645"
    },
    {
      "@id": "http://id.worldcat.org/fast/1424368"
    }
  ],
  "schema:associatedMedia": {
    "@id": "@base:/media/AnomaliesCuriosities_1981.pdf"
  },
  "schema:creator": "University of California, Davis. School of Medicine",
  "schema:datePublished": {
    "@type": "http://www.w3.org/2001/XMLSchema#gYear",
    "@value": "1981"
  },
  "schema:identifier": [
    "AR-096",
    "ark:/87293/d3183467c"
  ],
  "schema:image": {
    "@id": "@base:/media/images/AnomaliesCuriosities_1981_001.tif"
  },
  "schema:license": {
    "@id": "http://rightsstatements.org/vocab/InC-NC/1.0/"
  },
  "schema:name": "1981 Anomalies and Curiosities of Medicine",
  "schema:publisher": "University of California, Davis School of Medicine",
  "schema:sdDatePublished": {
    "@type": "http://www.w3.org/2001/XMLSchema#gYear",
    "@value": "2022"
  },
  "schema:sdLicense": {
    "@id": "http://rightsstatements.org/vocab/InC-NC/1.0/"
  },
  "schema:sdPublisher": [
    "UC Davis, Archives and Special Collections",
    {
      "@id": "http://id.loc.gov/authorities/names/no2008108707"
    }
  ]
}